baas_sms_mcp/__init__.py
baas_sms_mcp/py.typed
baas_sms_mcp/server.py
baas_sms_mcp-1.0.25.dist-info/METADATA
baas_sms_mcp-1.0.25.dist-info/WHEEL
baas_sms_mcp-1.0.25.dist-info/licenses/LICENSE
baas_sms_mcp-1.0.25.dist-info/RECORD
