Metadata-Version: 2.4
Name: baas-sms-mcp
Version: 1.0.25
Summary: A Model Context Protocol server for SMS and MMS messaging services
Project-URL: Homepage, https://github.com/your-org/baas-sms-mcp
Project-URL: Repository, https://github.com/your-org/baas-sms-mcp.git
Project-URL: Issues, https://github.com/your-org/baas-sms-mcp/issues
Project-URL: Documentation, https://github.com/your-org/baas-sms-mcp#readme
Author-email: mBaaS Team <support@aiapp.link>
License-Expression: MIT
License-File: LICENSE
Keywords: mcp,messaging,mms,model-context-protocol,sms
Classifier: Development Status :: 4 - Beta
Classifier: Intended Audience :: Developers
Classifier: License :: OSI Approved :: MIT License
Classifier: Operating System :: OS Independent
Classifier: Programming Language :: Python :: 3
Classifier: Programming Language :: Python :: 3.10
Classifier: Programming Language :: Python :: 3.11
Classifier: Programming Language :: Python :: 3.12
Classifier: Topic :: Communications
Classifier: Topic :: Software Development :: Libraries :: Python Modules
Requires-Python: >=3.10
Requires-Dist: httpx>=0.24.0
Requires-Dist: mcp>=0.2.0
Provides-Extra: dev
Requires-Dist: black>=23.0; extra == 'dev'
Requires-Dist: mypy>=1.0; extra == 'dev'
Requires-Dist: pytest-asyncio>=0.21.0; extra == 'dev'
Requires-Dist: pytest>=7.0; extra == 'dev'
Requires-Dist: ruff>=0.1.0; extra == 'dev'
